gemini_ocr/__init__.py
gemini_ocr/bbox_alignment.py
gemini_ocr/docai.py
gemini_ocr/docai_layout.py
gemini_ocr/docai_ocr.py
gemini_ocr/docling.py
gemini_ocr/document.py
gemini_ocr/gemini.py
gemini_ocr/gemini_ocr.py
gemini_ocr/range_ops.py
gemini_ocr/settings.py
gemini_ocr-0.4.0.dist-info/METADATA
gemini_ocr-0.4.0.dist-info/WHEEL
gemini_ocr-0.4.0.dist-info/licenses/LICENSE
gemini_ocr-0.4.0.dist-info/RECORD
