Metadata-Version: 2.4
Name: gemini-ocr
Version: 0.4.0
Summary: Hybrid OCR with gemini and DocumentAI
Project-URL: Homepage, https://github.com/folded/gemini-ocr
Project-URL: Bug Tracker, https://github.com/folded/gemini-ocr/issues
Author-email: Tobias Sargeant <tobias.sargeant@gmail.com>
License: MIT
License-File: LICENSE
Classifier: License :: OSI Approved :: MIT License
Classifier: Operating System :: OS Independent
Classifier: Programming Language :: Python :: 3
Classifier: Programming Language :: Python :: 3.11
Classifier: Programming Language :: Python :: 3.12
Classifier: Programming Language :: Python :: 3.13
Requires-Python: >=3.11
Requires-Dist: fsspec
Requires-Dist: gcsfs
Requires-Dist: google-cloud-documentai
Requires-Dist: google-genai
Requires-Dist: pymupdf
Requires-Dist: python-dotenv>=1.2.1
Requires-Dist: seq-smith>=0.5.1
